arubaos_client/__init__.py
arubaos_client/client.py
arubaos_client-0.1.2.3.dist-info/LICENSE
arubaos_client-0.1.2.3.dist-info/METADATA
arubaos_client-0.1.2.3.dist-info/WHEEL
arubaos_client-0.1.2.3.dist-info/top_level.txt
arubaos_client-0.1.2.3.dist-info/RECORD
