Metadata-Version: 2.1
Name: arubaos-client
Version: 0.1.2.3
Summary: Aruba OS REST API Client.
Home-page: https://github.com/Selfnet/arubaos_client
Author: Marcel Fest
Author-email: marcelf@selfnet.de
License: MIT
Keywords: metric prometheus airhead aruba mobility access controller os arubaos
Platform: UNKNOWN
Classifier: Development Status :: 4 - Beta
Classifier: Intended Audience :: Developers
Classifier: License :: OSI Approved :: MIT License
Classifier: Programming Language :: Python :: 3
Requires-Dist: requests
Requires-Dist: pytimeparse
Provides-Extra: dev
Requires-Dist: pylint; extra == 'dev'
Requires-Dist: autopep8; extra == 'dev'
Requires-Dist: pep8; extra == 'dev'
Requires-Dist: PySocks; extra == 'dev'
Provides-Extra: socks
Requires-Dist: PySocks; extra == 'socks'
